lildb/__init__.py
lildb/column_types.py
lildb/db.py
lildb/enumcls.py
lildb/operations.py
lildb/rows.py
lildb/table.py
lildb-0.5.0.dist-info/METADATA
lildb-0.5.0.dist-info/WHEEL
lildb-0.5.0.dist-info/RECORD
