Metadata-Version: 2.1
Name: lildb
Version: 0.5.0
Summary: LilDB provides a simplified wrapper for SQLite3.
Home-page: https://github.com/StickKing/lildb
License: MIT
Author: Anton Panteleev
Author-email: mainsample@yandex.ru
Requires-Python: >=3.8,<4.0
Classifier: License :: OSI Approved :: MIT License
Classifier: Programming Language :: Python :: 3
Classifier: Programming Language :: Python :: 3.8
Classifier: Programming Language :: Python :: 3.9
Classifier: Programming Language :: Python :: 3.10
Classifier: Programming Language :: Python :: 3.11
Project-URL: Repository, https://github.com/StickKing/lildb
